{
    "projectId": "68a03ad10030ac53cb92",
    "endpoint": "https://fra.cloud.appwrite.io/v1",
    "projectName": "nutri-suppliers",
    "settings": {
        "services": {
            "account": true,
            "avatars": true,
            "databases": true,
            "locale": true,
            "health": true,
            "storage": true,
            "teams": true,
            "users": true,
            "sites": true,
            "functions": true,
            "graphql": true,
            "messaging": true
        },
        "auth": {
            "methods": {
                "jwt": true,
                "phone": true,
                "invites": true,
                "anonymous": true,
                "email-otp": true,
                "magic-url": true,
                "email-password": true
            },
            "security": {
                "duration": 31536000,
                "limit": 0,
                "sessionsLimit": 10,
                "passwordHistory": 0,
                "passwordDictionary": false,
                "personalDataCheck": false,
                "sessionAlerts": false,
                "mockNumbers": []
            }
        }
    },
    "buckets": [
        {
            "$id": "68a03b2600160922b23d",
            "$permissions": [],
            "fileSecurity": false,
            "name": "nutrisuppliers",
            "enabled": true,
            "maximumFileSize": 50000000,
            "allowedFileExtensions": [],
            "compression": "none",
            "encryption": true,
            "antivirus": true
        }
    ],
    "functions": [
        {
            "$id": "uploadimagefunc",
            "name": "upload-image",
            "runtime": "node-18.0",
            "specification": "s-0.5vcpu-512mb",
            "execute": [
                "any"
            ],
            "events": [],
            "scopes": [
                "users.read",
                "buckets.read",
                "files.read",
                "files.write"
            ],
            "schedule": "",
            "timeout": 15,
            "enabled": true,
            "logging": true,
            "entrypoint": "src/main.js",
            "commands": "npm install",
            "path": "functions/upload-image"
        },
        {
            "$id": "deleteimagefunc",
            "name": "delete-image",
            "runtime": "node-18.0",
            "specification": "s-0.5vcpu-512mb",
            "execute": [
                "any"
            ],
            "events": [],
            "scopes": [
                "users.read",
                "buckets.read",
                "files.read",
                "files.write"
            ],
            "schedule": "",
            "timeout": 15,
            "enabled": true,
            "logging": true,
            "entrypoint": "src/main.js",
            "commands": "npm install",
            "path": "functions/delete-image"
        }
    ]
}